reformat_macs2.py
reformat_macs2-0.0.2.dist-info/METADATA
reformat_macs2-0.0.2.dist-info/WHEEL
reformat_macs2-0.0.2.dist-info/licenses/LICENSE
reformat_macs2-0.0.2.dist-info/RECORD
